image_to_pdf/__init__.py
image_to_pdf/py.typed
image_to_pdf-0.2.0.dist-info/LICENSE.txt
image_to_pdf-0.2.0.dist-info/METADATA
image_to_pdf-0.2.0.dist-info/WHEEL
image_to_pdf-0.2.0.dist-info/top_level.txt
image_to_pdf-0.2.0.dist-info/RECORD
