Metadata-Version: 2.2
Name: image-to-pdf
Version: 0.2.0
Summary: Convert image files to PDF.
Author: Jeffrey A. Clark, stefan6419846 (standalone conversion package)
License: MIT-CMU
Project-URL: Homepage, https://github.com/stefan6419846/image-to-pdf
Project-URL: Repository, https://github.com/stefan6419846/image-to-pdf
Project-URL: Issues, https://github.com/stefan6419846/image-to-pdf/issues
Project-URL: Changelog, https://github.com/stefan6419846/image-to-pdf/blob/main/CHANGELOG.md
Keywords: image,pdf,conversion
Classifier: Development Status :: 4 - Beta
Classifier: Intended Audience :: Developers
Classifier: License :: OSI Approved :: CMU License (MIT-CMU)
Classifier: Programming Language :: Python :: 3
Classifier: Programming Language :: Python :: 3 :: Only
Classifier: Topic :: Multimedia :: Graphics
Classifier: Topic :: Multimedia :: Graphics :: Graphics Conversion
Classifier: Topic :: Utilities
Classifier: Typing :: Typed
Requires-Python: <4,>=3.9
License-File: LICENSE.txt
Requires-Dist: Pillow
Provides-Extra: dev
Requires-Dist: flake8; extra == "dev"
Requires-Dist: flake8-bugbear; extra == "dev"
Requires-Dist: pep8-naming; extra == "dev"
Requires-Dist: coverage[toml]; extra == "dev"
Requires-Dist: requests; extra == "dev"
Requires-Dist: pypdf; extra == "dev"
Requires-Dist: codespell; extra == "dev"
